muhomor/__init__.py
muhomor/cli.py
muhomor/commands.py
muhomor/exceptions.py
muhomor/registry.py
muhomor/shell.py
muhomor/ext/__init__.py
muhomor/ext/falcon_rpc_middleware.py
muhomor/rpc/__init__.py
muhomor/rpc/cluster.py
muhomor/rpc/config.py
muhomor/rpc/entry_points.py
muhomor/rpc/transport.py
muhomor/rpc/worker.py
muhomor/utils/__init__.py
muhomor/utils/config.py
muhomor/utils/filesystem.py
muhomor/utils/functional.py
muhomor/utils/logging.py
muhomor/utils/serialization.py
muhomor/utils/text.py
muhomor/utils/sqlalchemy/__init__.py
muhomor/utils/sqlalchemy/ext.py
muhomor/utils/sqlalchemy/dialects/__init__.py
muhomor/utils/sqlalchemy/dialects/mysql.py
muhomor-1.0.0.dist-info/LICENSE
muhomor-1.0.0.dist-info/METADATA
muhomor-1.0.0.dist-info/WHEEL
muhomor-1.0.0.dist-info/top_level.txt
muhomor-1.0.0.dist-info/RECORD
